lgvad/__init__.py
lgvad/main.py
lgvad-1.0.0.dist-info/LICENSE
lgvad-1.0.0.dist-info/METADATA
lgvad-1.0.0.dist-info/WHEEL
lgvad-1.0.0.dist-info/entry_points.txt
lgvad-1.0.0.dist-info/top_level.txt
lgvad-1.0.0.dist-info/RECORD
