Metadata-Version: 2.1
Name: lgvad
Version: 1.0.0
Summary: very helpful lottery
Home-page: https://github.com/VadimTrubay/lgvad.git
Author: Trubay_Vadim
Author-email: vadnetvadnet@ukr.net
License: MIT
License-File: LICENSE
Requires-Dist: colorama
